{"status":"done","publicPath":"/static/","chunks":{"vendor":[{"name":"js/vendor.e642ca3b758f4a9e37af.js","publicPath":"/static/js/vendor.e642ca3b758f4a9e37af.js","path":"D:\\Code\\pokerface\\dist\\js\\vendor.e642ca3b758f4a9e37af.js"},{"name":"js/vendor.e642ca3b758f4a9e37af.js.map","publicPath":"/static/js/vendor.e642ca3b758f4a9e37af.js.map","path":"D:\\Code\\pokerface\\dist\\js\\vendor.e642ca3b758f4a9e37af.js.map"}],"app":[{"name":"js/app.fa05142c2bb6a5678419.js","publicPath":"/static/js/app.fa05142c2bb6a5678419.js","path":"D:\\Code\\pokerface\\dist\\js\\app.fa05142c2bb6a5678419.js"},{"name":"css/app.9059a4975463c40d47647e097efd240f.css","publicPath":"/static/css/app.9059a4975463c40d47647e097efd240f.css","path":"D:\\Code\\pokerface\\dist\\css\\app.9059a4975463c40d47647e097efd240f.css"},{"name":"js/app.fa05142c2bb6a5678419.js.map","publicPath":"/static/js/app.fa05142c2bb6a5678419.js.map","path":"D:\\Code\\pokerface\\dist\\js\\app.fa05142c2bb6a5678419.js.map"}],"manifest":[{"name":"js/manifest.9f596046247e86cce96d.js","publicPath":"/static/js/manifest.9f596046247e86cce96d.js","path":"D:\\Code\\pokerface\\dist\\js\\manifest.9f596046247e86cce96d.js"},{"name":"js/manifest.9f596046247e86cce96d.js.map","publicPath":"/static/js/manifest.9f596046247e86cce96d.js.map","path":"D:\\Code\\pokerface\\dist\\js\\manifest.9f596046247e86cce96d.js.map"}]}}