{"status":"done","publicPath":"/static/","chunks":{"vendor":[{"name":"js/vendor.d8acde5125ec02d965d8.js","publicPath":"/static/js/vendor.d8acde5125ec02d965d8.js","path":"D:\\Code\\pokerface\\dist\\js\\vendor.d8acde5125ec02d965d8.js"},{"name":"js/vendor.d8acde5125ec02d965d8.js.map","publicPath":"/static/js/vendor.d8acde5125ec02d965d8.js.map","path":"D:\\Code\\pokerface\\dist\\js\\vendor.d8acde5125ec02d965d8.js.map"}],"app":[{"name":"js/app.259aa5ca38e1b267ead2.js","publicPath":"/static/js/app.259aa5ca38e1b267ead2.js","path":"D:\\Code\\pokerface\\dist\\js\\app.259aa5ca38e1b267ead2.js"},{"name":"css/app.9e0646eff8bdadfd649276b0a6cf2482.css","publicPath":"/static/css/app.9e0646eff8bdadfd649276b0a6cf2482.css","path":"D:\\Code\\pokerface\\dist\\css\\app.9e0646eff8bdadfd649276b0a6cf2482.css"},{"name":"js/app.259aa5ca38e1b267ead2.js.map","publicPath":"/static/js/app.259aa5ca38e1b267ead2.js.map","path":"D:\\Code\\pokerface\\dist\\js\\app.259aa5ca38e1b267ead2.js.map"}],"manifest":[{"name":"js/manifest.bdae51221b4c243a762f.js","publicPath":"/static/js/manifest.bdae51221b4c243a762f.js","path":"D:\\Code\\pokerface\\dist\\js\\manifest.bdae51221b4c243a762f.js"},{"name":"js/manifest.bdae51221b4c243a762f.js.map","publicPath":"/static/js/manifest.bdae51221b4c243a762f.js.map","path":"D:\\Code\\pokerface\\dist\\js\\manifest.bdae51221b4c243a762f.js.map"}]}}